cloudiplookup/__init__.py
cloudiplookup/cloudiplookup.dat.gz
cloudiplookup/cloudiplookup.json
cloudiplookup/cloudiplookup.py
cloudiplookup-1.0.6.dist-info/LICENSE
cloudiplookup-1.0.6.dist-info/METADATA
cloudiplookup-1.0.6.dist-info/WHEEL
cloudiplookup-1.0.6.dist-info/entry_points.txt
cloudiplookup-1.0.6.dist-info/top_level.txt
cloudiplookup-1.0.6.dist-info/RECORD
