Metadata-Version: 2.1
Name: cloudiplookup
Version: 1.0.6
Summary: Cloud IP Lookup is a Pure Python application and library for Python 3 to verify which cloud platform a given IP address belongs to (AWS, Azure, Cloudflare, DigitalOcean, Google Services/Cloud, JD Cloud and Oracle Cloud).
Home-page: https://github.com/rabuchaim/cloudiplookup
Author: Ricardo Abuchaim
Author-email: ricardoabuchaim@gmail.com
Maintainer: Ricardo Abuchaim
Maintainer-email: ricardoabuchaim@gmail.com
License: MIT
Project-URL: Source Code, https://github.com/rabuchaim/cloudiplookup/tree/main/cloudiplookup
Project-URL: Issue Tracker, https://github.com/rabuchaim/cloudiplookup/issues
Keywords: cloudiplookup,cloud ip lookup,geoip,aws,azure,gcp,pure-python,purepython,pure python,oracle cloud,oci,digitalocean,digital ocean
Classifier: Development Status :: 5 - Production/Stable
Classifier: Topic :: Internet
Classifier: Topic :: System :: Networking
Classifier: Topic :: System :: Networking :: Monitoring
Classifier: Topic :: System :: Monitoring
Classifier: Topic :: System :: Networking
Classifier: Topic :: System :: Networking :: Monitoring
Classifier: Topic :: System :: Systems Administration
Classifier: Topic :: Software Development :: Libraries :: Python Modules
Classifier: Topic :: Utilities
Classifier: Environment :: Web Environment
Classifier: Intended Audience :: Developers
Classifier: Intended Audience :: Information Technology
Classifier: Intended Audience :: System Administrators
Classifier: License :: OSI Approved :: MIT License
Classifier: Programming Language :: Python
Classifier: Programming Language :: Python :: 3
Classifier: Programming Language :: Python :: 3.0
Classifier: Programming Language :: Python :: 3.1
Classifier: Programming Language :: Python :: 3.2
Classifier: Programming Language :: Python :: 3.3
Classifier: Programming Language :: Python :: 3.4
Classifier: Programming Language :: Python :: 3.5
Classifier: Programming Language :: Python :: 3.6
Classifier: Programming Language :: Python :: 3.7
Classifier: Programming Language :: Python :: 3.8
Classifier: Programming Language :: Python :: 3.9
Classifier: Programming Language :: Python :: 3.10
Classifier: Programming Language :: Python :: 3.11
Classifier: Programming Language :: Python :: 3.12
Classifier: Programming Language :: Python :: 3.13
Classifier: Programming Language :: Python :: Implementation :: PyPy
License-File: LICENSE
